Workbook

Sheet summary
A1: Total Inventory | B1: =COUNT(inventory!H2:H10735) -> 714 | D1: Sold Items With Expenses | G1: Sold Items Without Expenses
A2: # Sold | B2: =COUNTIF(inventory!J2:J1735,"Y") -> 406 | D2: Item Cost Price | E2: =SUMIF(inventory!J:J,"Y",inventory!H:H) -> 248101 | G2: Item Cost Price | H2: =SUMIF(inventory!J:J,"Y",inventory!H:H) -> 248101
A3: #Unsold | B3: =B1-B2 -> 308 | D3: Expenses | E3: =B9+B10 -> 98890 | G3: Item Sell Price | H3: =SUMIF(inventory!J:J,"Y",inventory!K:K) -> 333353
A4: Total Inventory Cost | B4: =SUM(inventory!H2:H1736) -> 422546 | D4: Total Cost | E4: =E2+E3 -> 346991 | G4: Profit/Loss | H4: =H3-H2 -> 85252
D5: Item Sell Price | E5: =SUMIF(inventory!J:J,"Y",inventory!K:K) -> 333353 | G5: Margin | H5: =H4/H2 -> 0.34361812
A6: Expense Type | B6: Cost | D6: Profit/Loss | E6: =E5-E4 -> -13638
A7: Garments | B7: =SUMIF(Table2[Expense Type],summary!A7,Table2[Cost]) -> 422546 | C7: =B7-B4 -> 0 | D7: Margin | E7: =E6/E4 -> -0.039303613
A8: Transport | B8: =SUMIF(Table2[Expense Type],summary!A8,Table2[Cost]) -> 0
A9: Misc | B9: =SUMIF(Table2[Expense Type],summary!A9,Table2[Cost]) -> 10045
A10: Rent | B10: =SUMIF(Table2[Expense Type],summary!A10,Table2[Cost]) -> 88845
A11: Total | B11: =SUM(B7+B9+B10) -> 521436
A13: Tanaya Share | B13: 100000
A14: Shampa Share | B14: 100000
A15: Total Investment | B15: =B13+B14 -> 200000
A16: Money Left in Bank | B16: =B15-B11+E5 -> 11917 | C16: 84143

Sheet expense
A1: Sr | B1: Date | C1: Item | D1: Shop Name | E1: Contact | F1: Expense Type | G1: Cost | P1: Expense Type
A2: 1 | B2: 45426 | C2: Garments | D2: Soma Collection | E2: 9123632189 ,8910547566 | F2: Garments | G2: 14800 | P2: Garments
A3: 2 | B3: 45433 | C3: Garments | D3: N G Garments | E3: 7029968104 | F3: Garments | G3: 26355 | P3: Misc
A4: 3 | B4: 45435 | C4: Ring Light | D4: Barobazar | E4: NA | F4: Misc | G4: 2850 | P4: Rent
A5: 4 | B5: 45435 | C5: Packing meterials + sticker | D5: Souvik Palit | E5: 8296100622, 7278523077 | F5: Misc | G5: 770
A6: 5 | B6: 45438 | C6: 1st live payment | D6: Paromita's BTM | E6: NA | F6: Rent | G6: 201
A7: 6 | B7: 45456 | C7: Garments | D7: Rudra Fashion | E7: 9674577149, 7439467048 | F7: Garments | G7: 8095
A8: 7 | B8: 45457 | C8: Shapoorji Exhibition rent | D8: Sristi | E8: NA | F8: Rent | G8: 2500
A9: 8 | B9: 45459 | C9: Garments | D9: Soma Collection | E9: 9123632189 ,8910547566 | F9: Garments | G9: 1265
A10: 9 | B10: 45460 | C10: Garments | D10: Rudra Fashion | E10: NA | F10: Garments | G10: 11750
A11: 10 | B11: 45461 | C11: Exhibition item | D11: local shop | E11: NA | F11: Misc | G11: 310
A12: 11 | B12: 45468 | C12: Laketown Exhibition (6th sep-8th sep) | D12: Arindam da | E12: 9051860399 | F12: Rent | G12: 4000
A13: 12 | B13: 45470 | C13: Company Visiting Card(100) | D13: Palashi printingwork | E13: 9830067722 | F13: Misc | G13: 250
A14: 13 | B14: 45470 | C14: Exhibition item | D14: Local shop | E14: NA | F14: Misc | G14: 150
A15: 14 | B15: 45476 | C15: Agamani2 Indira Moidan(10th Aug- 11th Aug)+chair | D15: Tamojit Ghosh | E15: 8420846124 | F15: Rent | G15: 3524
A16: 15 | B16: 45476 | C16: Danlop, Bonhoogly Exhibition (12th Jul - 14th Jul) | D16: Dwitipriya Dutta | E16: 7980278100 | F16: Rent | G16: 1500
A17: 16 | B17: 45481 | C17: Garments | D17: RV Fashions | E17: 9007839660, 9674288512 | F17: Garments | G17: 4670
A18: 17 | B18: 45503 | C18: Garments | D18: Surana Fashion | F18: Garments | G18: 5488
A19: 18 | B19: 45506 | C19: Garments | D19: Rudra Fashion | F19: Garments | G19: 12810
A20: 19 | B20: 45531 | C20: Garments | D20: Rudra Fashion | F20: Garments | G20: 16000
A21: 20 | B21: 45538 | C21: Garments | D21: Apna Andaaz | F21: Garments | G21: 9160
A22: 21 | B22: 45538 | C22: Garments Stand | D22: mayur hanger mart | F22: Misc | G22: 1350
A23: 22 | B23: 45538 | C23: Return Gift item | D23: NA | F23: Misc | G23: 320
A24: 23 | B24: 45538 | C24: Hanger + Clip + Bag | D24: NA | F24: Misc | G24: 390
A25: 24 | B25: 45539 | C25: Banner | D25: Palashi printingwork | E25: 9830067722 | F25: Misc | G25: 350
A26: 25 | B26: 45485 | C26: Sahachori | D26: NA | F26: Rent | G26: 350
A27: 26 | B27: 45545 | C27: Srijoni Club Exibition Rent | D27: NA | F27: Rent | G27: 2200
A28: 27 | B28: 45546 | C28: garments | D28: RV Fashions | F28: Garments | G28: 4740
A29: 28 | B29: 45548 | C29: Karunamoyee Jagotdhatri puja exhib(november) | D29: Arindam da | E29: 9051860399 | F29: Rent | G29: 4300
A30: 29 | B30: 45553 | C30: Garments | D30: Rudra Fashion | F30: Garments | G30: 16155
A31: 30 | B31: 45608 | C31: Carry Bags | D31: NA | F31: Misc | G31: 150
A32: 31 | B32: 45619 | C32: Garments | D32: Asmita Saree Palace | F32: Garments | G32: 7550
A33: 32 | B33: 45621 | C33: Garments | D33: RV Fashions | F33: Garments | G33: 5950
A34: 33 | B34: 45623 | C34: Garments | D34: Rudra Fashion | F34: Garments | G34: 11100
A35: 34 | B35: 45638 | C35: Exhibition jessorRoad HORI SHOVA(14Dec-15Dec) | D35: Badol Chowdhury | E35: 8337087694 | F35: Rent | G35: 2000
A36: 35 | B36: 45642 | C36: Kashi Bose Lane Exhib (Jan16,Jan17,Jan18,Jan19) | D36: Arinesh Banerjee | E36: 9073106009 | F36: Rent | G36: 4300
A37: 36 | B37: 45643 | C37: Laketown Exhib rent (3th April-6th April) | D37: Arindam da | E37: 9051860399 | F37: Rent | G37: 4000
A38: 37 | B38: 45669 | C38: Das vila (25th, 26th january) | D38: Puspita | F38: Rent | G38: 2000
A39: 38 | B39: 45696 | C39: BK Pal (13,14,15,16,17)march | D39: Arinesh Banerjee | E39: 9073106009 | F39: Rent | G39: 1000
A40: 39 | B40: 45733 | C40: Garments | D40: RV Fashions | F40: Garments | G40: 5680
A41: 40 | B41: 45695 | C41: Light | D41: NA | F41: Misc | G41: 350
A42: 41 | B42: 45687 | C42: Company Visiting Card(100) | D42: Palashi printingwork | E42: 9830067722 | F42: Misc | G42: 250
A43: 42 | B43: 45731 | C43: Chetla Central Park(29th-30th-31th March) | D43: Rent | E43: 9123029644 | F43: Rent | G43: 1890
A44: 43 | B44: 45736 | C44: Garments | D44: Satyam Fashion | F44: Garments | G44: 11640
A45: 44 | B45: 45740 | C45: Garments | D45: Ajit Kumar Das | E45: 9476263474 | F45: Garments | G45: 4980
A46: 45 | B46: 45757 | C46: Garments | D46: Rudra Fashion | F46: Garments | G46: 9935
A47: 46 | B47: 45757 | C47: Behala Borisha Club(11th April-14th April) | D47: Priyodorshini 555 Kolkata | E47: 8910206398 | F47: Rent | G47: 4000
A48: 47 | B48: 45757 | C48: Laketown Exhibition (5th sep-7th sep) + chair(10/day) | D48: Arindam da | E48: 9051860399 | F48: Rent | G48: 4280
A49: 48 | B49: 45765 | C49: Garments | D49: Kaaruk | F49: Garments | G49: 3730
A50: 49 | B50: 45799 | C50: Garment | D50: Bongo Nari | E50: 9163244658 | F50: Garments | G50: 5000
A51: 50 | B51: 45799 | C51: Garment | D51: N G Garments | E51: 9007514155, 8370838601 | F51: Garments | G51: 19613
A52: 51 | B52: 45832 | C52: Garment | D52: Surana Fashion | F52: Garments | G52: 6220
A53: 52 | B53: 45832 | C53: Bansdroni Brahmapur club(16th July-20thJuly) | D53: Priyodorshini 555 Kolkata | E53: 8910206398 | F53: Rent | G53: 7000
A54: 53 | B54: 45832 | C54: Lords Bakery More Padatik(22th,23th,24th,25th August) | D54: Priyodorshini 555 Kolkata | E54: 8910206398 | F54: Rent | G54: 7000
A55: 54 | B55: 45845 | C55: gift | D55: NA | F55: Misc | G55: 400
A56: 55 | B56: 45845 | C56: Plastic sheet | D56: NA | F56: Misc | G56: 100
A57: 56 | B57: 45845 | C57: product packing bags | D57: NA | F57: Misc | G57: 290
A58: 57 | B58: 45845 | C58: Big Bags (6) | D58: NA | F58: Misc | G58: 850
A59: 58 | B59: 45845 | C59: Bill Book + sticker | D59: NA | F59: Misc | G59: 355
A60: 59 | B60: 45848 | C60: Garment | D60: RV Fashions | F60: Garments | G60: 19310
A61: 60 | B61: 45889 | C61: Garment | D61: Rudra Fashion | F61: Garments | G61: 20295
A62: 61 | B62: 45890 | C62: Carry Bags(200) | D62: NA | F62: Misc | G62: 560
A63: 62 | B63: 45898 | C63: Behala Chonditala (29th Augus & 30th August) | D63: NA | F63: Rent | G63: 1500
A64: 63 | B64: 45898 | C64: Garments | D64: Rudra Fashion | F64: Garments | G64: 4735
A65: 64 | B65: 45903 | C65: Garments | D65: Kaaruk | F65: Garments | G65: 8080
A66: 65 | B66: 45911 | C66: Basdroni shakti Shangh Exhib(19thsept-22nd sept) | D66: Priyodorshini 555 Kolkata | F66: Rent | G66: 7000
... A68: 67 | B68: 45912 | C68: Garment +Sompa Black Gown | D68: Rudra Fashion | F68: Garments | G68: 20500
A69: 68 | B69: 45938 | C69: Laketown winter Exhibition (18th,19th,20th,21st Dec) | D69: Arindam da | E69: 9051860399 | F69: Rent | G69: 4250
A70: 69 | B70: 45973 | C70: Garments | D70: Ridhi Sidhi Fashion | F70: Garments | G70: 5150
A71: 70 | B71: 45973 | C71: Garments | D71: Anukul Dresses | F71: Garments | G71: 18460
A72: 71 | B72: 46001 | C72: Ranikuthi Exibition(12th 13th 14th 15th 16th Dec) | D72: Priyodorshini 555 Kolkata | F72: Rent | G72: 6500
A73: 72 | B73: 46002 | C73: Garments | D73: Kaaruk | F73: Garments | G73: 11180
A74: 73 | B74: 46029 | C74: Garments | D74: Rudra Fashion | F74: Garments | G74: 31150
A75: 74 | B75: 46029 | C75: Kalindi winter Exhibition (8th,9th,10th,11st Jan) | D75: Arindam da | F75: Rent | G75: 4250
A76: 75 | B76: 46034 | C76: Laketown Bangure Avu(5th-8th March) | D76: Arindam da | F76: Rent | G76: 4500
A77: 76 | B77: 46078 | C77: Garments | D77: ASG Dream Fashion | F77: Garments | G77: 33630
A78: 77 | B78: 46080 | C78: Garments | D78: Rudra Fashion | F78: Garments | G78: 27370

Sheet inventory
A1: Sr | B1: Bill No. | C1: Type | D1: Item Description | E1: Material | F1: Shop Name | G1: Avl Size | H1: Buy Price | I1: Price Tag | J1: Sold | K1: Sold Price | L1: Sold To | M1: Column1
A2: 1 | B2: padatik | C2: Dress | D2: Dress (High-low) , Sea green with red flower, Round Neck, show buttens in front | E2: Cotton | F2: N G Garments | G2: XXL | H2: 699 | I2: 899 | J2: Y | K2: 832 | L2: R. Mukherjee | M2: =VLOOKUP(Table3[[#This Row],[Shop Name]],seller!A:A,1,0) -> N G Garments
A3: 2 | B3: 9 | C3: Dress | D3: Dress (High-low) , Sea green with red flower, Round Neck, show buttens in front | E3: Cotton | F3: N G Garments | G3: XL | H3: 699 | I3: 899 | J3: Y | K3: 850 | L3: Sumit Sapoorji | M3: =VLOOKUP(Table3[[#This Row],[Shop Name]],seller!A:A,1,0) -> N G Garments
A4: 3 | B4: 9 | C4: Dress | D4: Dress (High-low) , Sea green with red flower, Round Neck, show buttens in front | E4: Cotton | F4: N G Garments | G4: L | H4: 699 | I4: 899 | J4: Y | K4: 850 | L4: Lake Town seller | M4: =VLOOKUP(Table3[[#This Row],[Shop Name]],seller!A:A,1,0) -> N G Garments
A5: 4 | B5: 5 | C5: Dress | D5: Gray Long shrug, Bright green colour inside, Round neck, sleeveless inside and 3 quarter sleeves shrug | E5: Cotton | F5: N G Garments | G5: L | H5: 799 | I5: 999 | J5: Y | K5: 900 | L5: Bijita Roy | M5: =VLOOKUP(Table3[[#This Row],[Shop Name]],seller!A:A,1,0) -> N G Garments
A6: 5 | B6: 5 | C6: Dress | D6: Ochre Yellow Long shrug, Black colour inside, shrug is in ochre colour with maroon colour print, Round neck sleeveless inside and 3 quarter sleeves shrug | E6: Cotton | F6: N G Garments | G6: XXL | H6: 799 | I6: 999 | J6: Y | K6: 980 | L6: sujata (indira moidan) | M6: =VLOOKUP(Table3[[#This Row],[Shop Name]],seller!A:A,1,0) -> N G Garments
A7: 6 | B7: 5 | C7: Dress | D7: Ochre Yellow Long shrug, Black colour inside, shrug is in ochre colour with maroon colour print, Round neck sleeveless inside and 3 quarter sleeves shrug | E7: Cotton | F7: N G Garments | G7: XL | H7: 799 | I7: 999 | J7: Y | K7: 949 | L7: Susmita Bhowmik | M7: =VLOOKUP(Table3[[#This Row],[Shop Name]],seller!A:A,1,0) -> N G Garments
A8: 7 | B8: 5 | C8: Dress | D8: Ochre Yellow Long shrug, Black colour inside, shrug is in ochre colour with maroon colour print, Round neck sleeveless inside and 3 quarter sleeves shrug | E8: Cotton | F8: N G Garments | G8: L | H8: 799 | I8: 999 | J8: Y | K8: 950 | L8: shilpi Das | M8: =VLOOKUP(Table3[[#This Row],[Shop Name]],seller!A:A,1,0) -> N G Garments
A9: 8 | B9: 8 | C9: Sleeveless kurti | D9: Rapid Aline Kurti, In ochre yellow olive and blue rapid print, Shirt collar, one side pocket, wooden show buttons in front, slit at the end | E9: Cotton | F9: N G Garments | G9: XXL | H9: 555 | I9: 755 | J9: Y | K9: 700 | L9: Sunita Rath(Emami) | M9: =VLOOKUP(Table3[[#This Row],[Shop Name]],seller!A:A,1,0) -> N G Garments
A10: 9 | B10: 8 | C10: Sleeveless kurti | D10: Rapid Aline Kurti, In ochre yellow olive and blue rapid print, Shirt collar, one side pocket, wooden show buttons in front, slit at the end | E10: Cotton | F10: N G Garments | G10: XL | H10: 555 | I10: 755 | J10: Y | K10: 555 | L10: Tanaya(Owner) | M10: =VLOOKUP(Table3[[#This Row],[Shop Name]],seller!A:A,1,0) -> N G Garments
A11: 10 | B11: 8 | C11: Sleeveless kurti | D11: Rapid Aline Kurti, In ochre yellow olive and blue rapid print, Shirt collar, one side pocket, wooden show buttons in front, slit at the end | E11: Cotton | F11: N G Garments | G11: L | H11: 555 | I11: 755 | J11: Y | K11: 600 | L11: Piu | M11: =VLOOKUP(Table3[[#This Row],[Shop Name]],seller!A:A,1,0) -> N G Garments
A12: 11 | B12: Padatik | C12: Sleeveless kurti | D12: Rapid Aline Kurti, In ochre yellow olive and blue rapid print, Shirt collar, one side pocket, wooden show buttons in front, slit at the end | E12: Cotton | F12: N G Garments | G12: M | H12: 555 | I12: 755 | J12: Y | K12: 680 | L12: Putul Karmakar Padatik | M12: =VLOOKUP(Table3[[#This Row],[Shop Name]],seller!A:A,1,0) -> N G Garments
A13: 12 | B13: 7 | C13: Sleeveless kurti | D13: Ajrakh Aline Kurti, White colour with red black and blue ajrakh hand printed, Shirt collar, one side pocket, wooden show buttons in front, slit at the end | E13: Cotton | F13: N G Garments | G13: XXL | H13: 499 | I13: 699 | J13: Y | K13: 699 | L13: Debjani Sarkar | M13: =VLOOKUP(Table3[[#This Row],[Shop Name]],seller!A:A,1,0) -> N G Garments
A14: 13 | B14: 7 | C14: Sleeveless kurti | D14: Ajrakh Aline Kurti, White colour with red black and blue ajrakh hand printed, Shirt collar, one side pocket, wooden show buttons in front, slit at the end | E14: Cotton | F14: N G Garments | G14: L | H14: 499 | I14: 699 | J14: Y | K14: 643 | L14: Rituparna Das | M14: =VLOOKUP(Table3[[#This Row],[Shop Name]],seller!A:A,1,0) -> N G Garments
A15: 14 | B15: 7 | C15: Sleeveless kurti | D15: Ajrakh Aline Kurti, White colour with red black and blue ajrakh hand printed, Shirt collar, one side pocket, wooden show buttons in front, slit at the end | E15: Cotton | F15: N G Garments | G15: M | H15: 499 | I15: 699 | J15: Y | K15: 499 | L15: Sompa (owner) | M15: =VLOOKUP(Table3[[#This Row],[Shop Name]],seller!A:A,1,0) -> N G Garments
A16: 15 | B16: 6 | C16: Quarter sleeves Kurti | D16: Malai Cotton Kurti, model silk border, Magenta colour with model silk print border, V neck, one side pocket, 3 quarter sleeves, both sides slit at the end | E16: Malai Cotton | F16: N G Garments | G16: XXL | H16: 545 | I16: 750 | J16: Y | K16: 670 | L16: Mousumi Behala chondi. | M16: =VLOOKUP(Table3[[#This Row],[Shop Name]],seller!A:A,1,0) -> N G Garments
A17: 16 | B17: Karu | C17: Quarter sleeves Kurti | D17: Malai Cotton Kurti, Bottle green colour with model silk print border, V neck, one side pocket, 3 quarter sleeves, both sides slit at the end | E17: Malai Cotton | F17: N G Garments | G17: XXL | H17: 545 | I17: 750 | J17: Y | K17: 688 | L17: Surangana | M17: =VLOOKUP(Table3[[#This Row],[Shop Name]],seller!A:A,1,0) -> N G Garments
A18: 17 | B18: 10 | C18: 3 Piece co-ord set | D18: 3 Piece co-ord set, White with green floral print, straight paint, noodle top, long shrug | E18: Cotton | F18: N G Garments | G18: XXL | H18: 810 | I18: 1025 | J18: Y | K18: 900 | L18: Arpita Behala | M18: =VLOOKUP(Table3[[#This Row],[Shop Name]],seller!A:A,1,0) -> N G Garments
A19: 18 | B19: 10 | C19: 3 Piece co-ord set | D19: 3 Piece co-ord set, White with orange floral print, straight paint, noodle top, long shrug | E19: Cotton | F19: N G Garments | G19: XXL | H19: 725 | I19: 1025 | J19: Y | K19: 725 | L19: Tanaya(Owner) | M19: =VLOOKUP(Table3[[#This Row],[Shop Name]],seller!A:A,1,0) -> N G Garments
A20: 19 | B20: 1 | C20: Dress | D20: Boyfrnd dress, White strip on Red colour, Shirt collar button in fount | E20: Cotton | F20: N G Garments | G20: M | H20: 499 | I20: 699 | J20: Y | K20: 499 | L20: Sompa (owner) | M20: =VLOOKUP(Table3[[#This Row],[Shop Name]],seller!A:A,1,0) -> N G Garments
A21: 20 | B21: 1 | C21: Dress | D21: Boyfrnd dress, White strip on Black Colour, Shirt collar button in fount | E21: Cotton | F21: N G Garments | G21: M | H21: 499 | I21: 699 | J21: Y | K21: 499 | L21: Sompa (owner) | M21: =VLOOKUP(Table3[[#This Row],[Shop Name]],seller!A:A,1,0) -> N G Garments
A22: 21 | B22: 2 | C22: Dress | D22: Black, short shrug maroon Ajrakh print, Round neck sleeveless inside and 3 quarter sleeves short shrug | E22: Cotton | F22: N G Garments | G22: XXL | H22: 599 | I22: 799 | J22: Y | K22: 750 | L22: Sharmista | M22: =VLOOKUP(Table3[[#This Row],[Shop Name]],seller!A:A,1,0) -> N G Garments
A23: 22 | B23: 2 | C23: Dress | D23: Black, short shrug maroon Ajrakh print, Round neck sleeveless inside and 3 quarter sleeves short shrug | E23: Cotton | F23: N G Garments | G23: XL | H23: 599 | I23: 799 | J23: Y | K23: 799 | L23: Davi | M23: =VLOOKUP(Table3[[#This Row],[Shop Name]],seller!A:A,1,0) -> N G Garments
A24: 23 | B24: 2 | C24: Dress | D24: Black, short shrug maroon Ajrakh print, Round neck sleeveless inside and 3 quarter sleeves short shrug | E24: Cotton | F24: N G Garments | G24: L | H24: 599 | I24: 799 | J24: Y | K24: 799 | L24: Joyita Banik | M24: =VLOOKUP(Table3[[#This Row],[Shop Name]],seller!A:A,1,0) -> N G Garments
A25: 24 | B25: 3 | C25: Dress | D25: Red, short shrug Rapid print short shrug in sea green colour with red colour rapid print, Round neck, sleeveless inside and 3 quarter sleeves short shrug | E25: Cotton | F25: N G Garments | G25: XXL | H25: 655 | I25: 855 | J25: Y | K25: 775 | L25: Ranjana | M25: =VLOOKUP(Table3[[#This Row],[Shop Name]],seller!A:A,1,0) -> N G Garments
A26: 25 | B26: 3 | C26: Dress | D26: Red, short shrug Rapid print short shrug in sea green colour with red colour rapid print, Round neck, sleeveless inside and 3 quarter sleeves short shrug | E26: Cotton | F26: N G Garments | G26: XL | H26: 655 | I26: 855 | J26: Y | K26: 800 | L26: Shampa Sarkar | M26: =VLOOKUP(Table3[[#This Row],[Shop Name]],seller!A:A,1,0) -> N G Garments
A27: 26 | B27: 3 | C27: Dress | D27: Red, short shrug Rapid print short shrug in sea green colour with red colour rapid print, Round neck, sleeveless inside and 3 quarter sleeves short shrug | E27: Cotton | F27: N G Garments | G27: L | H27: 655 | I27: 855 | J27: Y | K27: 655 | L27: Tanaya(Owner) | M27: =VLOOKUP(Table3[[#This Row],[Shop Name]],seller!A:A,1,0) -> N G Garments
A28: 27 | B28: Karu | C28: Dress | D28: Yellow, with short shrug in dark green with yellow colour rapid print, Round neck sleeveless inside and 3 quarter sleeves short shrug | E28: Cotton | F28: N G Garments | G28: XXL | H28: 655 | I28: 855 | J28: Y | K28: 780 | L28: Tuhina Biswas | M28: =VLOOKUP(Table3[[#This Row],[Shop Name]],seller!A:A,1,0) -> N G Garments
A29: 28 | B29: 3 | C29: Dress | D29: Yellow, with short shrug in dark green with yellow colour rapid print, Round neck sleeveless inside and 3 quarter sleeves short shrug | E29: Cotton | F29: N G Garments | G29: XL | H29: 655 | I29: 855 | J29: Y | K29: 800 | L29: Shampa Sarkar | M29: =VLOOKUP(Table3[[#This Row],[Shop Name]],seller!A:A,1,0) -> N G Garments
A30: 29 | B30: 3 | C30: Dress | D30: Yellow , with short shrug in dark green with yellow colour rapid print, Round neck sleeveless inside and 3 quarter sleeves short shrug | E30: Cotton | F30: N G Garments | G30: L | H30: 655 | I30: 855 | J30: Y | K30: 800 | L30: Souravi Sur | M30: =VLOOKUP(Table3[[#This Row],[Shop Name]],seller!A:A,1,0) -> N G Garments
A31: 30 | B31: 4 | C31: 2 Piece | D31: Yellow, green floral, straight paint, Square neck, 3 show buttons in Front, sleeveless | E31: Cotton | F31: N G Garments | G31: XXL | H31: 750 | I31: 950 | J31: Y | K31: 880 | L31: Sukla | M31: =VLOOKUP(Table3[[#This Row],[Shop Name]],seller!A:A,1,0) -> N G Garments
A32: 31 | B32: 4 | C32: 2 Piece | D32: Yellow, green floral, straight paint, Square neck, 3 show buttons in Front, sleeveless | E32: Cotton | F32: N G Garments | G32: XL | H32: 750 | I32: 950 | J32: Y | K32: 950 | L32: Sudipta | M32: =VLOOKUP(Table3[[#This Row],[Shop Name]],seller!A:A,1,0) -> N G Garments
A33: 32 | B33: 4 | C33: 2 Piece | D33: Yellow, green floral, straight paint, Square neck, 3 show buttons in Front, sleeveless | E33: Cotton | F33: N G Garments | G33: L | H33: 750 | I33: 950 | J33: Y | K33: 750 | L33: Sompa (owner) | M33: =VLOOKUP(Table3[[#This Row],[Shop Name]],seller!A:A,1,0) -> N G Garments
A34: 33 | B34: 4 | C34: 2 Piece | D34: Yellow, green floral, straight paint, Square neck, 3 show buttons in Front, sleeveless | E34: Cotton | F34: N G Garments | G34: M | H34: 750 | I34: 950 | J34: Y | K34: 750 | L34: Sompa(ownar) | M34: =VLOOKUP(Table3[[#This Row],[Shop Name]],seller!A:A,1,0) -> N G Garments
A35: 34 | B35: 4 | C35: 2 Piece | D35: Sky Blue, straight paint, square neck kurti with 3 show buttons in Front, sleeveless | E35: Cotton | F35: N G Garments | G35: XXL | H35: 750 | I35: 950 | J35: Y | K35: 880 | L35: S.Das | M35: =VLOOKUP(Table3[[#This Row],[Shop Name]],seller!A:A,1,0) -> N G Garments
A36: 35 | B36: 4 | C36: 2 Piece | D36: Sky Blue, straight paint, square neck kurti with 3 show buttons in Front, sleeveless | E36: Cotton | F36: N G Garments | G36: XL | H36: 750 | I36: 950 | J36: Y | K36: 750 | L36: Sipra Mukherjee | M36: =VLOOKUP(Table3[[#This Row],[Shop Name]],seller!A:A,1,0) -> N G Garments
A37: 36 | B37: Laketown (Dec) | C37: 2 Piece | D37: Sky Blue, straight paint, square neck kurti with 3 show buttons in Front, sleeveless | E37: Cotton | F37: N G Garments | G37: L | H37: 750 | I37: 950 | J37: Y | K37: 900 | L37: lia Dhor | M37: =VLOOKUP(Table3[[#This Row],[Shop Name]],seller!A:A,1,0) -> N G Garments
A38: 37 | B38: 4 | C38: 2 Piece | D38: Sky Blue, straight paint, square neck kurti with 3 show buttons in Front, sleeveless | E38: Cotton | F38: N G Garments | G38: M | H38: 750 | I38: 950 | J38: N | K38: 0 | M38: =VLOOKUP(Table3[[#This Row],[Shop Name]],seller!A:A,1,0) -> N G Garments
A39: 38 | B39: Sakti Sangha | C39: 2 Piece | D39: Black & White Set, Round neck, straight paint, Lace work | E39: Cotton | F39: Soma Collection | G39: XXL | H39: 595 | I39: 795 | J39: Y | K39: 750 | L39: Naegish Parvin | M39: =VLOOKUP(Table3[[#This Row],[Shop Name]],seller!A:A,1,0) -> Soma Collection
A40: 39 | B40: 7 | C40: 2 Piece | D40: Black & White Set, Round neck, straight paint, Lace work | E40: Cotton | F40: Soma Collection | G40: XL | H40: 595 | I40: 795 | J40: Y | K40: 795 | L40: Sudipta | M40: =VLOOKUP(Table3[[#This Row],[Shop Name]],seller!A:A,1,0) -> Soma Collection
A41: 40 | B41: 7 | C41: 2 Piece | D41: Black & White Set, Round neck, straight paint, Lace work | E41: Cotton | F41: Soma Collection | G41: L | H41: 595 | I41: 795 | J41: Y | K41: 595 | L41: Tanaya(Owner) | M41: =VLOOKUP(Table3[[#This Row],[Shop Name]],seller!A:A,1,0) -> Soma Collection
A42: 41 | B42: Sakti Sangha | C42: 2 Piece | D42: Black & White Set, Round neck, straight paint, Lace work | E42: Cotton | F42: Soma Collection | G42: M | H42: 595 | I42: 795 | J42: Y | K42: 700 | L42: Moumita | M42: =VLOOKUP(Table3[[#This Row],[Shop Name]],seller!A:A,1,0) -> Soma Collection
A43: 42 | B43: 3 | C43: Dress | D43: Baby Pink, mirror work with belt | E43: shifon | F43: Soma Collection | G43: M | H43: 695 | I43: 895 | J43: Y | K43: 695 | L43: Sompa (owner) | M43: =VLOOKUP(Table3[[#This Row],[Shop Name]],seller!A:A,1,0) -> Soma Collection
A44: 43 | B44: 3 | C44: Dress | D44: Baby Pink, mirror work with belt | E44: shifon | F44: Soma Collection | G44: M | H44: 695 | I44: 895 | J44: N | K44: 0 | M44: =VLOOKUP(Table3[[#This Row],[Shop Name]],seller!A:A,1,0) -> Soma Collection
A45: 44 | B45: 6 | C45: Dress | D45: Pink, Bandhani Print Gown | E45: shifon | F45: Soma Collection | G45: Free | H45: 550 | I45: 750 | J45: Y | K45: 650 | L45: Indira | M45: =VLOOKUP(Table3[[#This Row],[Shop Name]],seller!A:A,1,0) -> Soma Collection
A46: 45 | B46: 6 | C46: Dress | D46: Red, Bandhani Print Gown | E46: shifon | F46: Soma Collection | G46: Free | H46: 550 | I46: 750 | J46: Y | K46: 550 | L46: Sompa (owner) | M46: =VLOOKUP(Table3[[#This Row],[Shop Name]],seller!A:A,1,0) -> Soma Collection
A47: 46 | B47: padatik | C47: 2 piece | D47: V neck Blue and white floral print, Quarter sleeves | E47: Cotton | F47: Rudra Fashion | G47: XL | H47: 0 | I47: 775 | J47: Y | K47: 708 | L47: R. Mukherjee | M47: =VLOOKUP(Table3[[#This Row],[Shop Name]],seller!A:A,1,0) -> Rudra Fashion
A48: 47 | B48: - | C48: 2 piece | D48: V neck Blue and white floral print, Quarter sleeves | E48: Cotton | F48: Rudra Fashion | G48: 3XL | H48: 575 | I48: 775 | J48: Y | K48: 720 | L48: Purnima Jadav | M48: =VLOOKUP(Table3[[#This Row],[Shop Name]],seller!A:A,1,0) -> Rudra Fashion
A49: 48 | B49: padatik | C49: 2 Piece | D49: V neck Green and white floral print, Quarter sleeves | E49: Cotton | F49: Rudra Fashion | G49: XXL | H49: 575 | I49: 775 | J49: Y | K49: 708 | L49: R. Mukherjee | M49: =VLOOKUP(Table3[[#This Row],[Shop Name]],seller!A:A,1,0) -> Rudra Fashion
A50: 49 | B50: - | C50: 2 Piece | D50: Round neck, purple colour, Quarter sleeves | E50: Cotton | F50: Soma Collection | G50: XL | H50: 570 | I50: 770 | J50: Y | K50: 700 | L50: Moumita Das-sapoo | M50: =VLOOKUP(Table3[[#This Row],[Shop Name]],seller!A:A,1,0) -> Soma Collection
A51: 50 | B51: - | C51: 2 Piece | D51: Round neck, purple colour, Quarter sleeves | E51: Cotton | F51: Soma Collection | G51: XXL | H51: 570 | I51: 770 | J51: Y | K51: 750 | L51: Snikdha Saha | M51: =VLOOKUP(Table3[[#This Row],[Shop Name]],seller!A:A,1,0) -> Soma Collection
A52: 51 | B52: - | C52: 2 Piece | D52: Round neck, peach colour, Quarter sleeves | E52: Cotton | F52: Soma Collection | G52: XL | H52: 570 | I52: 770 | J52: Y | K52: 700 | L52: Chatla Customer | M52: =VLOOKUP(Table3[[#This Row],[Shop Name]],seller!A:A,1,0) -> Soma Collection
A53: 52 | B53: - | C53: 2 Piece | D53: Round neck, Mustard Yellow colour, Quarter sleeves | E53: Cotton | F53: Soma Collection | G53: XXL | H53: 570 | I53: 770 | J53: Y | K53: 750 | L53: Bandana Shing | M53: =VLOOKUP(Table3[[#This Row],[Shop Name]],seller!A:A,1,0) -> Soma Collection
A54: 53 | B54: - | C54: 2 Piece | D54: Round neck, Mustard Yellow colour, Quarter sleeves | E54: Cotton | F54: Soma Collection | G54: XL | H54: 570 | I54: 770 | J54: Y | K54: 750 | L54: Priyanka Roy | M54: =VLOOKUP(Table3[[#This Row],[Shop Name]],seller!A:A,1,0) -> Soma Collection
A55: 54 | B55: Kalindi | C55: 2 Piece | D55: V neck White with Blue flower print, Quarter sleeves | E55: Cotton | F55: Rudra Fashion | G55: XL | H55: 575 | I55: 775 | J55: Y | K55: 700 | L55: Muskan | M55: =VLOOKUP(Table3[[#This Row],[Shop Name]],seller!A:A,1,0) -> Rudra Fashion
A56: 55 | B56: - | C56: 2 Piece | D56: V neck White with Blue flower print, Quarter sleeves | E56: Cotton | F56: Rudra Fashion | G56: L | H56: 575 | I56: 775 | J56: N | K56: 0 | M56: =VLOOKUP(Table3[[#This Row],[Shop Name]],seller!A:A,1,0) -> Rudra Fashion
A57: 56 | B57: - | C57: Short top | D57: Pink, Round Neck, Sleeveless | E57: Cotton | F57: Rudra Fashion | G57: XL | H57: 145 | I57: 345 | J57: N | K57: 0 | M57: =VLOOKUP(Table3[[#This Row],[Shop Name]],seller!A:A,1,0) -> Rudra Fashion
A58: 57 | B58: - | C58: Short top | D58: Yellow, Round Neck, Sleeveless | E58: Cotton | F58: Rudra Fashion | G58: L | H58: 145 | I58: 345 | J58: Y | K58: 300 | L58: Behala cust | M58: =VLOOKUP(Table3[[#This Row],[Shop Name]],seller!A:A,1,0) -> Rudra Fashion
A59: 58 | B59: - | C59: Short top | D59: Green, Round Neck, Sleeveless | E59: Cotton | F59: Rudra Fashion | G59: L | H59: 145 | I59: 345 | J59: N | K59: 0 | M59: =VLOOKUP(Table3[[#This Row],[Shop Name]],seller!A:A,1,0) -> Rudra Fashion
A60: 59 | B60: - | C60: Dress | D60: Pink, Shirt collar, Sleeveless | E60: Cotton | F60: Rudra Fashion | G60: XXL | H60: 465 | I60: 665 | J60: Y | K60: 650 | L60: Krishna(srijoni) | M60: =VLOOKUP(Table3[[#This Row],[Shop Name]],seller!A:A,1,0) -> Rudra Fashion
A61: 60 | B61: Padatik | C61: Dress | D61: Sea Green, Shirt collar, Sleeveless | E61: Cotton | F61: Rudra Fashion | G61: XXL | H61: 465 | I61: 665 | J61: Y | K61: 550 | L61: Moushumi Padatik | M61: =VLOOKUP(Table3[[#This Row],[Shop Name]],seller!A:A,1,0) -> Rudra Fashion
A62: 61 | B62: - | C62: Dress | D62: Yellow, Shirt collar, Sleeveless | E62: Cotton | F62: Rudra Fashion | G62: XL | H62: 465 | I62: 665 | J62: Y | K62: 665 | L62: Sudipta | M62: =VLOOKUP(Table3[[#This Row],[Shop Name]],seller!A:A,1,0) -> Rudra Fashion
A63: 62 | B63: - | C63: Dress | D63: Yellow, Shirt collar, Sleeveless | E63: Cotton | F63: Rudra Fashion | G63: L | H63: 465 | I63: 665 | J63: Y | K63: 665 | L63: Bubli Didi | M63: =VLOOKUP(Table3[[#This Row],[Shop Name]],seller!A:A,1,0) -> Rudra Fashion
A64: 63 | B64: - | C64: Dress | D64: Yellow, Shirt collar, Sleeveless | E64: Cotton | F64: Rudra Fashion | G64: L | H64: 465 | I64: 665 | J64: Y | K64: 600 | L64: Preeti Kumari Sapoorji | M64: =VLOOKUP(Table3[[#This Row],[Shop Name]],seller!A:A,1,0) -> Rudra Fashion
A65: 64 | B65: - | C65: Dress | D65: Yellow, Shirt collar, Sleeveless | E65: Cotton | F65: Rudra Fashion | G65: XXL | H65: 465 | I65: 665 | J65: Y | K65: 665 | L65: Sipra Mukherjee | M65: =VLOOKUP(Table3[[#This Row],[Shop Name]],seller!A:A,1,0) -> Rudra Fashion
A66: 65 | B66: - | C66: Dress | D66: Yellow, Shirt collar, Sleeveless | E66: Cotton | F66: Rudra Fashion | G66: XXL | H66: 465 | I66: 665 | J66: Y | K66: 650 | L66: Shamoli Sarkar | M66: =VLOOKUP(Table3[[#This Row],[Shop Name]],seller!A:A,1,0) -> Rudra Fashion
A67: 66 | B67: - | C67: Dress | D67: Purple, Round Neck, Sleeveless | E67: Cotton | F67: Rudra Fashion | G67: XL | H67: 415 | I67: 615 | J67: Y | K67: 590 | L67: Lata | M67: =VLOOKUP(Table3[[#This Row],[Shop Name]],seller!A:A,1,0) -> Rudra Fashion
A68: 67 | B68: - | C68: Dress | D68: Blue with White Flower, Round Neck, Sleeveless | E68: Cotton | F68: Soma Collection | G68: XL | H68: 420 | I68: 620 | J68: Y | K68: 571 | L68: Panchali Sapoorji | M68: =VLOOKUP(Table3[[#This Row],[Shop Name]],seller!A:A,1,0) -> Soma Collection
A69: 68 | B69: - | C69: Dress | D69: Black with White Flower, Round Neck, Sleeveless | E69: Cotton | F69: Soma Collection | G69: 3XL | H69: 420 | I69: 620 | J69: Y | K69: 550 | L69: Sayantani | M69: =VLOOKUP(Table3[[#This Row],[Shop Name]],seller!A:A,1,0) -> Soma Collection
A70: 69 | B70: - | C70: Quarter sleeves Kurti | D70: Red, Round neck, light thread works in front | E70: Cotton | F70: Soma Collection | G70: XXL | H70: 295 | I70: 495 | J70: N | K70: 0 | M70: =VLOOKUP(Table3[[#This Row],[Shop Name]],seller!A:A,1,0) -> Soma Collection
A71: 70 | B71: - | C71: Quarter sleeves Kurti | D71: Navy Blue, Round neck, light thread works in front | E71: Cotton | F71: Soma Collection | G71: XXL | H71: 295 | I71: 495 | J71: N | K71: 0 | M71: =VLOOKUP(Table3[[#This Row],[Shop Name]],seller!A:A,1,0) -> Soma Collection
A72: 71 | B72: Laketown (Dec) | C72: Quarter sleeves Kurti | D72: Green, Round neck, light thread works in front | E72: Cotton | F72: Soma Collection | G72: 3XL | H72: 295 | I72: 495 | J72: Y | K72: 450 | L72: Shuli Ghosh | M72: =VLOOKUP(Table3[[#This Row],[Shop Name]],seller!A:A,1,0) -> Soma Collection
A73: 72 | B73: - | C73: Quarter sleeves Kurti | D73: Robin Blue, Round neck, light thread works in front | E73: Cotton | F73: Soma Collection | G73: XL | H73: 295 | I73: 495 | J73: N | K73: 0 | M73: =VLOOKUP(Table3[[#This Row],[Shop Name]],seller!A:A,1,0) -> Soma Collection
A74: 73 | B74: - | C74: Quarter sleeves Kurti | D74: Purple with white floral print, Round neck, light thread works in front | E74: Cotton | F74: Soma Collection | G74: XL | H74: 395 | I74: 595 | J74: Y | K74: 595 | L74: Puja | M74: =VLOOKUP(Table3[[#This Row],[Shop Name]],seller!A:A,1,0) -> Soma Collection
A75: 74 | B75: - | C75: Quarter sleeves Kurti | D75: SkyBlue with white floral print, Round neck, light thread works in front | E75: Cotton | F75: Soma Collection | G75: XXL | H75: 395 | I75: 595 | J75: Y | K75: 300 | L75: Behala cust | M75: =VLOOKUP(Table3[[#This Row],[Shop Name]],seller!A:A,1,0) -> Soma Collection
A76: 75 | B76: - | C76: Quarter sleeves Kurti | D76: SkyBlue with white floral print, Round neck, light thread works in front | E76: Cotton | F76: Soma Collection | G76: XL | H76: 395 | I76: 595 | J76: Y | K76: 550 | L76: Anindita Chakraborty | M76: =VLOOKUP(Table3[[#This Row],[Shop Name]],seller!A:A,1,0) -> Soma Collection
A77: 76 | B77: - | C77: Quarter sleeves Kurti | D77: Yellow with white floral print, round neck, light thread works in front | E77: Cotton | F77: Soma Collection | G77: XXL | H77: 395 | I77: 595 | J77: Y | K77: 580 | L77: Chaitali Mukherjee | M77: =VLOOKUP(Table3[[#This Row],[Shop Name]],seller!A:A,1,0) -> Soma Collection
A78: 77 | B78: - | C78: Quarter sleeves Kurti | D78: Yellow, kalamkari print, aplic with DUCK thread works in front | E78: Cotton | F78: Soma Collection | G78: L | H78: 230 | I78: 430 | J78: Y | K78: 300 | L78: Behala cust | M78: =VLOOKUP(Table3[[#This Row],[Shop Name]],seller!A:A,1,0) -> Soma Collection
A79: 78 | B79: - | C79: Quarter sleeves Kurti | D79: Blue, kalamkari print,Round neck, aplic with DUCK thread works in front | E79: Cotton | F79: Soma Collection | G79: L | H79: 230 | I79: 430 | J79: Y | K79: 400 | L79: Piu | M79: =VLOOKUP(Table3[[#This Row],[Shop Name]],seller!A:A,1,0) -> Soma Collection
A80: 79 | B80: Laketown (Dec) | C80: Quarter sleeves Kurti | D80: Green,kalamkari print, Round neck, aplic with DUCK thread works in front | E80: Cotton | F80: Soma Collection | G80: L | H80: 230 | I80: 430 | J80: Y | K80: 380 | L80: Rakhi | M80: =VLOOKUP(Table3[[#This Row],[Shop Name]],seller!A:A,1,0) -> Soma Collection
A81: 80 | B81: - | C81: Quarter sleeves Kurti | D81: Maroon, kalamkari print, Round neck, aplic with DUCK thread works in front | E81: Cotton | F81: Soma Collection | G81: L | H81: 230 | I81: 430 | J81: N | K81: 0 | M81: =VLOOKUP(Table3[[#This Row],[Shop Name]],seller!A:A,1,0) -> Soma Collection
A82: 81 | B82: - | C82: Quarter sleeves Kurti | D82: Red with Floral print, V neck | E82: Cotton | F82: Soma Collection | G82: L | H82: 395 | I82: 595 | J82: Y | K82: 571 | L82: Panchali Sapoorji | M82: =VLOOKUP(Table3[[#This Row],[Shop Name]],seller!A:A,1,0) -> Soma Collection
A83: 82 | B83: - | C83: Quarter sleeves Kurti | D83: Yellow with Floral print, V neck | E83: Cotton | F83: Soma Collection | G83: XL | H83: 395 | I83: 595 | J83: Y | K83: 550 | L83: Anindita Chakraborty | M83: =VLOOKUP(Table3[[#This Row],[Shop Name]],seller!A:A,1,0) -> Soma Collection
A84: 83 | B84: - | C84: Quarter sleeves Kurti | D84: Robin Blue with Floral print, V neck | E84: Cotton | F84: Soma Collection | G84: XXL | H84: 395 | I84: 595 | J84: N | K84: 0 | M84: =VLOOKUP(Table3[[#This Row],[Shop Name]],seller!A:A,1,0) -> Soma Collection
A85: 84 | B85: - | C85: Quarter sleeves Kurti | D85: Black with Floral print, V neck | E85: Cotton | F85: Soma Collection | G85: XXL | H85: 395 | I85: 595 | J85: Y | K85: 550 | L85: Sankari Banik | M85: =VLOOKUP(Table3[[#This Row],[Shop Name]],seller!A:A,1,0) -> Soma Collection
A86: 85 | B86: - | C86: Quarter sleeves Kurti | D86: Chocolate Brown, angrakha | E86: Cotton | F86: Rudra Fashion | G86: XXL | H86: 425 | I86: 625 | J86: Y | K86: 625 | L86: S.Panda | M86: =VLOOKUP(Table3[[#This Row],[Shop Name]],seller!A:A,1,0) -> Rudra Fashion
A87: 86 | B87: - | C87: Quarter sleeves Kurti | D87: Chocolate Brown, angrakha | E87: Cotton | F87: Rudra Fashion | G87: L | H87: 425 | I87: 625 | J87: Y | K87: 600 | L87: Piu | M87: =VLOOKUP(Table3[[#This Row],[Shop Name]],seller!A:A,1,0) -> Rudra Fashion
A88: 87 | B88: * | C88: Quarter sleeves Kurti | D88: Red-White-Black kurti, Round Neck, thread work | E88: Cotton | F88: Rudra Fashion | G88: XL | H88: 360 | I88: 560 | J88: Y | K88: 511 | L88: Susmita Bhowmik | M88: =VLOOKUP(Table3[[#This Row],[Shop Name]],seller!A:A,1,0) -> Rudra Fashion
A89: 88 | B89: * | C89: Quarter sleeves Kurti | D89: Black-White-Red kurti, Round Neck, thread work | E89: Cotton | F89: Rudra Fashion | G89: XL | H89: 360 | I89: 560 | J89: N | K89: 0 | M89: =VLOOKUP(Table3[[#This Row],[Shop Name]],seller!A:A,1,0) -> Rudra Fashion
A90: 89 | B90: - | C90: Quarter sleeves Kurti | D90: Pink, V Neck, angrakha style, thread work | E90: Cotton | F90: Rudra Fashion | G90: XL | H90: 345 | I90: 545 | J90: Y | K90: 500 | L90: S.Mukherjee | M90: =VLOOKUP(Table3[[#This Row],[Shop Name]],seller!A:A,1,0) -> Rudra Fashion
A91: 90 | B91: - | C91: Quarter sleeves Kurti | D91: Pink, Round Neck, angrakha style thread work | E91: Cotton | F91: Rudra Fashion | G91: L | H91: 395 | I91: 595 | J91: N | K91: 0 | M91: =VLOOKUP(Table3[[#This Row],[Shop Name]],seller!A:A,1,0) -> Rudra Fashion
A92: 91 | B92: 3 | C92: Quarter sleeves Kurti | D92: Maroon, Round Neck, Ajrakh print & thread work in front | E92: Cotton | F92: Rudra Fashion | G92: M | H92: 485 | I92: 685 | J92: N | K92: 0 | M92: =VLOOKUP(Table3[[#This Row],[Shop Name]],seller!A:A,1,0) -> Rudra Fashion
A93: 92 | B93: 5 | C93: Quarter sleeves Kurti | D93: Navy Blue, V Neck, Ajrakh Border around the neck | E93: Cotton | F93: Rudra Fashion | G93: M | H93: 485 | I93: 685 | J93: Y | K93: 600 | L93: Tripti | M93: =VLOOKUP(Table3[[#This Row],[Shop Name]],seller!A:A,1,0) -> Rudra Fashion
A94: 93 | B94: - | C94: Quarter sleeves Kurti | D94: Maroon, V Neck, thread work in front | E94: Reyon | F94: Rudra Fashion | G94: L | H94: 385 | I94: 585 | J94: Y | K94: 585 | L94: Arpita Saha | M94: =VLOOKUP(Table3[[#This Row],[Shop Name]],seller!A:A,1,0) -> Rudra Fashion
A95: 94 | C95: Noodle Kurti | D95: Zed black, Molmol,sleeveless, print and light thread work in front | E95: Cotton | F95: Rudra Fashion | G95: M | H95: 525 | I95: 725 | J95: Y | K95: 675 | L95: Sathi Chakraborty | M95: =VLOOKUP(Table3[[#This Row],[Shop Name]],seller!A:A,1,0) -> Rudra Fashion
A96: 95 | C96: Noodle Kurti | D96: Zed black, Molmol,sleeveless, print and light thread work in front | E96: Cotton | F96: Rudra Fashion | G96: 3XL | H96: 525 | I96: 725 | J96: Y | K96: 725 | L96: Piyali | M96: =VLOOKUP(Table3[[#This Row],[Shop Name]],seller!A:A,1,0) -> Rudra Fashion
A97: 96 | B97: - | C97: Noodle Kurti | D97: Zed black, Molmol,sleeveless, print and light thread work in front | E97: Cotton | F97: Rudra Fashion | G97: L | H97: 525 | I97: 725 | J97: Y | K97: 650 | L97: Nidhi Kumari | M97: =VLOOKUP(Table3[[#This Row],[Shop Name]],seller!A:A,1,0) -> Rudra Fashion
A98: 97 | B98: - | C98: Noodle Kurti | D98: Ochre Yellow, sleeveless, print and light thread work in front | E98: Cotton | F98: Rudra Fashion | G98: 3XL | H98: 485 | I98: 685 | J98: Y | K98: 650 | L98: Shilp Saler (KBL) | M98: =VLOOKUP(Table3[[#This Row],[Shop Name]],seller!A:A,1,0) -> Rudra Fashion
A99: 98 | B99: - | C99: Noodle Kurti | D99: Ochre Yellow, sleeveless, print and light thread work in front | E99: Cotton | F99: Rudra Fashion | G99: M | H99: 485 | I99: 685 | J99: Y | K99: 685 | L99: Sujata | M99: =VLOOKUP(Table3[[#This Row],[Shop Name]],seller!A:A,1,0) -> Rudra Fashion
A100: 99 | B100: - | C100: Noodle Kurti | D100: Maroon sleeveless, All over print and light thread work | E100: Cotton | F100: Rudra Fashion | G100: XL | H100: 215 | I100: 415 | J100: Y | K100: 390 | L100: Aromita Saler (KBL) | M100: =VLOOKUP(Table3[[#This Row],[Shop Name]],seller!A:A,1,0) -> Rudra Fashion
...

Sheet customer
A1: title | B1: customer_name | C1: phone_1 | D1: phone_2 | E1: phone_3 | F1: email | G1: address | H1: city | I1: state | J1: country | K1: exhibition | L1: customer_type | M1: notes | N1: birthday | O1: anniversary
B2: Sunita Mitra | C2: 8981738522 | L2: ED Park Newtown
B3: Nisha | C3: 9439700760 | L3: ED Park Newtown
B4: Saujeeta | C4: 9733062387 | L4: ED Park Newtown
B5: Mala | C5: 9831621540 | L5: ED Park Newtown
B6: Nandita Debnath | C6: 9681136796 | L6: ED Park Newtown
B7: Sharmistha Banerjee | C7: 8617781358 | L7: ED Park Newtown
B8: S.Saha | C8: 9163062385 | L8: ED Park Newtown
B9: Souravi Sarkar | C9: 7797998586 | L9: ED Park Newtown
B10: Rituparna Das | C10: 9674697379 | L10: ED Park Newtown
B11: Sumita Goswami | C11: 8249193459 | L11: ED Park Newtown
B12: Bijita Roy | C12: 6294214930 | L12: ED Park Newtown
B13: Dhruba Mukherjee | C13: 9830535369 | L13: ED Park Newtown
... B30: Bhaswati Mukherjee | C30: 9051782373 | L30: Family
B31: Piyali | L31: Friend
B32: Debi | L32: Friend
B33: Joyita Banik | C33: 7003116699 | L33: Friend
B34: Sudipta | L34: Friend
B35: Sumit Sapoorji | C35: 9836108083 | L35: Sapoorji
B36: Preeti Kumari Sapoorji | C36: 7634029006 | L36: Sapoorji
B37: Panchali Sapoorji | C37: 9830949260 | L37: Sapoorji
B38: Moumita Das | C38: 9635923465 | L38: Sapoorji
B39: Sathi Chakraborty | C39: 9163136670 | L39: Sapoorji
B40: Souravi Sur | C40: 8583041496 | L40: Sapoorji
B41: Sipra Mukherjee | C41: 9051371731 | L41: Family
B42: Shika kakima | L42: Family
B43: Bandana Shing | C43: 7044253238 | L43: Bonhooghly
B44: Susmita Bhowmik | C44: 8442833958 | L44: Bonhooghly
B45: Purnima Jadav | C45: 8910436069 | L45: Bonhooghly
B46: Nidhi Kumari | C46: 9955480273 | L46: Indira Maidan
B47: Sujata | C47: 8777828231 | L47: Indira Maidan
B48: Arunima | C48: 9836694016 | L48: Indira Maidan
B49: Chaitali Mukherjee | C49: 7044062722 | L49: Indira Maidan
B50: Sharmista | C50: 8697039702 | L50: Indira Maidan
B51: Shilpi Das | C51: 8617204358 | L51: Indira Maidan
B52: Priyanka Roy | C52: 8622014282 | L52: Indira Maidan
B53: Tarun Chowdhury | C53: 9331063544 | L53: Indira Maidan
B54: Payel | C54: 7439603788 | L54: Srijoni club
... B94: Samohita Mondal | C94: 7003208782 | L94: Behala

Sheet transport

Sheet seller
A1: shop_name | B1: owner_name | C1: phone_1 | D1: phone_2 | E1: phone_3 | F1: email | G1: address | H1: landmark | I1: city | J1: state | K1: country | L1: minimum_purchase | M1: timings | N1: notes
A2: Kinnori Saree | C2: 8583075575 | D2: 9163338500 | G2: 201-B Mahatma Gandhi Road, Sadasukh Katra, 1st Floor, Kolkata -700007
A3: Shivam Cloth Stores | C3: 8910429158 | D3: 9875352598 | G3: 199/5, Mahatma Gandhi Road, Bholaram Katra, 2nd Floor, Kolkata-700007 | H3: Opposite to BoroBazar Gurudwara
A4: Nash Boutique | C4: 9339543013 | D4: 9831141481 | G4: Mullick Bazar, Dakshineswar, Kolkata, WB-700017 | M4: Everyday 12pm-8am Friday 1pm-8am
A5: N G Garments | C5: 9007514155 | D5: 8370838601 | G5: 2, Kolkata GA-90, Sector G, East Kolkata Township, Kolkata- 700107 | H5: Opposite GST Bhavan,Near Ruby Hospital | L5: 5000 | M5: Everyday 10:30am-8pm
A6: Soma Collection | C6: 8910547566 | D6: 9123632189 | G6: Barasaat, 15 Duckbanglow More, kolkata 700127 | L6: 3000 | M6: Everyday 10am-11pm
A7: Adhunika Exclusive | C7: 8583922908 | D7: 9830082180 | G7: 1st floor, Holding No.1643NO | H7: Bus stop- Ramkrishnagar ,Manikpur, Khailshakota Polly, Kolkata | M7: Mon-Sat 11am-7pm
A8: Lady Queen Wholesale Raghav Creation (Young Lady) | C8: 8337048137 | D8: 6292333700 | G8: 12/1 Nellie Sengupta Sarani,kol-87 | H8: New market | L8: 45000-50000 | M8: Everyday 11am-9pm
A9: Ashneh Creation | C9: 9830808296 | D9: 7980724031 | G9: P 82, Lake Town, Ward No 30, Block B, Kolkata-700089 | H9: Mansa Mandir | M9: Everyday 11:30am-7pm
A10: Aruna Textile Hub | C10: 9313801946 | D10: 6357099969 | G10: Surat Gujarat
A11: Sai Dhara NX | C11: 7567617394 | D11: 9687002692 | G11: Surat Gujarat | N11: 7567617394(Sachin), 9687002692(Alok)
A12: Gargee Creation | C12: 9051136072 | D12: 9830849110 | G12: Barabazar
A13: Rudra Fashion
A14: Surana Fashion | G14: mikelNager | M14: 11:00pm - 6:00pm
A15: Apna Andaaz | C15: 7980626679 | G15: LaxmiPlaza, Room No.-!17, 1stFloor, 6, Hanspukur Lane, Kolkata-700007
A16: Asmita Saree Palace | C16: 9434343491 | D16: 9153535351 | G16: Nutan Fulia
A17: Satyam Fashion | C17: 877351879 | D17: 7003462234 | G17: Jessore Road,Amarpally
A18: Ajit Kumar Das | C18: 9476263474 | G18: Dhanekhali Bazar,Hooghly
A19: Kaaruk Fashion | C19: 9874452973 | G19: Hridaypur, Barasat
A20: Bongo Nari | C20: 9163244658 | G20: Ruby Hospital | H20: Acropolic mall
A21: Anukul Dresses | C21: 9836374668 | D21: 7980375359 | G21: Sodhpur | N21: 9836374668(M),7980375359(W)
A22: Ridhi Sidhi Fashion | C22: 9831581005 | D22: 9875675303 | G22: Sodhpur
A23: ASG Dream Fashion | C23: 9836551405 | D23: 8820022704 | G23: Howrah
A24: RV Fashion | C24: 9007839660 | D24: 9674288512
A25: Kaaruk

Sheet product
A1: type | B1: description | C1: material | D1: color | E1: pattern | F1: neck_style | G1: other_details
A2: Dress | B2: Dress (High-low) , Sea green with red flower, Round Neck, show buttons in front | C2: Cotton | D2: Sea green with red flower | F2: Round Neck | G2: Dress (High-low); show buttons in front
A3: Dress | B3: Gray Long shrug, Bright green colour inside, Round neck, sleeveless inside and 3 quarter sleeves shrug | C3: Cotton | D3: Bright green colour inside | F3: Round neck | G3: Gray Long shrug; sleeveless inside and 3 quarter sleeves shrug
A4: Dress | B4: Ochre Yellow Long shrug, Black colour inside, shrug is in ochre colour with maroon colour print, Round neck sleeveless inside and 3 quarter sleeves shrug | C4: Cotton | D4: Ochre Yellow Long shrug; Black colour inside | E4: shrug is in ochre colour with maroon colour print | F4: Round neck sleeveless inside and 3 quarter sleeves shrug
A5: Sleeveless Kurti | B5: Rapid Aline Kurti, In ochre yellow olive and blue rapid print, Shirt collar, one side pocket, wooden show buttons in front, slit at the end | C5: Cotton | D5: In ochre yellow olive and blue rapid print | G5: Rapid Aline Kurti; Shirt collar; one side pocket; wooden show buttons in front; slit at the end
A6: Sleeveless Kurti | B6: Ajrakh Aline Kurti, White colour with red black and blue ajrakh hand printed, Shirt collar, one side pocket, wooden show buttons in front, slit at the end | C6: Cotton | D6: White colour with red black and blue ajrakh hand printed | G6: Ajrakh Aline Kurti; Shirt collar; one side pocket; wooden show buttons in front; slit at the end
A7: Quarter Sleeves Kurti | B7: Malai Cotton Kurti, model silk border, Magenta colour with model silk print border, V neck, one side pocket, 3 quarter sleeves, both sides slit at the end | C7: Malai Cotton | E7: Magenta colour with model silk print border | F7: V neck | G7: Malai Cotton Kurti; model silk border; one side pocket; 3 quarter sleeves; both sides slit at the end
A8: Quarter Sleeves Kurti | B8: Malai Cotton Kurti, Bottle green colour with model silk print border, V neck, one side pocket, 3 quarter sleeves, both sides slit at the end | C8: Malai Cotton | D8: Bottle green colour with model silk print border | F8: V neck | G8: Malai Cotton Kurti; one side pocket; 3 quarter sleeves; both sides slit at the end
A9: 3 Piece Co-Ord Set | B9: 3 Piece co-ord set, White with green floral print, straight paint, noodle top, long shrug | C9: Cotton | D9: White with green floral print | G9: 3 Piece co-ord set; straight paint; noodle top; long shrug
A10: 3 Piece Co-Ord Set | B10: 3 Piece co-ord set, White with orange floral print, straight paint, noodle top, long shrug | C10: Cotton | D10: White with orange floral print | G10: 3 Piece co-ord set; straight paint; noodle top; long shrug
A11: Dress | B11: Boyfrnd dress, White strip on Red colour, Shirt collar button in fount | C11: Cotton | D11: White strip on Red colour | G11: Boyfrnd dress; Shirt collar button in fount
A12: Dress | B12: Boyfrnd dress, White strip on Black Colour, Shirt collar button in fount | C12: Cotton | D12: White strip on Black Colour | G12: Boyfrnd dress; Shirt collar button in fount
A13: Dress | B13: Black, short shrug maroon Ajrakh print, Round neck sleeveless inside and 3 quarter sleeves short shrug | C13: Cotton | D13: Black | E13: short shrug maroon Ajrakh print | F13: Round neck sleeveless inside and 3 quarter sleeves short shrug
A14: Dress | B14: Red, short shrug Rapid print short shrug in sea green colour with red colour rapid print, Round neck, sleeveless inside and 3 quarter sleeves short shrug | C14: Cotton | D14: Red; short shrug Rapid print short shrug in sea green colour with red colour rapid print | F14: Round neck | G14: sleeveless inside and 3 quarter sleeves short shrug
A15: Dress | B15: Yellow, with short shrug in dark green with yellow colour rapid print, Round neck sleeveless inside and 3 quarter sleeves short shrug | C15: Cotton | D15: Yellow; with short shrug in dark green with yellow colour rapid print | F15: Round neck sleeveless inside and 3 quarter sleeves short shrug
A16: Dress | B16: Yellow , with short shrug in dark green with yellow colour rapid print, Round neck sleeveless inside and 3 quarter sleeves short shrug | C16: Cotton | D16: Yellow; with short shrug in dark green with yellow colour rapid print | F16: Round neck sleeveless inside and 3 quarter sleeves short shrug
A17: 2 Piece | B17: Yellow, green floral, straight paint, Square neck, 3 show buttons in Front, sleeveless | C17: Cotton | D17: Yellow; green floral | F17: Square neck | G17: straight paint; 3 show buttons in Front; sleeveless
A18: 2 Piece | B18: Sky Blue, straight paint, square neck kurti with 3 show buttons in Front, sleeveless | C18: Cotton | D18: Sky Blue | F18: square neck kurti with 3 show buttons in Front | G18: straight paint; sleeveless
A19: 2 Piece | B19: Black & White Set, Round neck, straight paint, Lace work | C19: Cotton | D19: Black & White Set | F19: Round neck | G19: straight paint; Lace work
A20: Dress | B20: Baby Pink, mirror work with belt | C20: Shifon | D20: Baby Pink | G20: mirror work with belt
A21: Dress | B21: Pink, Bandhani Print Gown | C21: Shifon | D21: Pink | E21: Bandhani Print Gown
A22: Dress | B22: Red, Bandhani Print Gown | C22: Shifon | D22: Red | E22: Bandhani Print Gown
A23: 2 Piece | B23: V neck Blue and white floral print, Quarter sleeves | C23: Cotton | D23: V neck Blue and white floral print | G23: Quarter sleeves
A24: 2 Piece | B24: V neck Green and white floral print, Quarter sleeves | C24: Cotton | D24: V neck Green and white floral print | G24: Quarter sleeves
A25: 2 Piece | B25: Round neck, purple colour, Quarter sleeves | C25: Cotton | F25: Round neck | G25: purple colour; Quarter sleeves
A26: 2 Piece | B26: Round neck, peach colour, Quarter sleeves | C26: Cotton | F26: Round neck | G26: peach colour; Quarter sleeves
A27: 2 Piece | B27: Round neck, Mustard Yellow colour, Quarter sleeves | C27: Cotton | D27: Mustard Yellow colour | F27: Round neck | G27: Quarter sleeves
A28: 2 Piece | B28: V neck White with Blue flower print, Quarter sleeves | C28: Cotton | D28: V neck White with Blue flower print | G28: Quarter sleeves
A29: Short Top | B29: Pink, Round Neck, Sleeveless | C29: Cotton | D29: Pink | F29: Round Neck | G29: Sleeveless
A30: Short Top | B30: Yellow, Round Neck, Sleeveless | C30: Cotton | D30: Yellow | F30: Round Neck | G30: Sleeveless
A31: Short Top | B31: Green, Round Neck, Sleeveless | C31: Cotton | D31: Green | F31: Round Neck | G31: Sleeveless
A32: Dress | B32: Pink, Shirt collar, Sleeveless | C32: Cotton | D32: Pink | G32: Shirt collar; Sleeveless
A33: Dress | B33: Sea Green, Shirt collar, Sleeveless | C33: Cotton | D33: Sea Green | G33: Shirt collar; Sleeveless
A34: Dress | B34: Yellow, Shirt collar, Sleeveless | C34: Cotton | D34: Yellow | G34: Shirt collar; Sleeveless
A35: Dress | B35: Purple, Round Neck, Sleeveless | C35: Cotton | F35: Round Neck | G35: Purple; Sleeveless
A36: Dress | B36: Blue with White Flower, Round Neck, Sleeveless | C36: Cotton | D36: Blue with White Flower | F36: Round Neck | G36: Sleeveless
A37: Dress | B37: Black with White Flower, Round Neck, Sleeveless | C37: Cotton | D37: Black with White Flower | F37: Round Neck | G37: Sleeveless
A38: Quarter Sleeves Kurti | B38: Red, Round neck, light thread works in front | C38: Cotton | D38: Red | F38: Round neck | G38: light thread works in front
A39: Quarter Sleeves Kurti | B39: Navy Blue, Round neck, light thread works in front | C39: Cotton | D39: Navy Blue | F39: Round neck | G39: light thread works in front
A40: Quarter Sleeves Kurti | B40: Green, Round neck, light thread works in front | C40: Cotton | D40: Green | F40: Round neck | G40: light thread works in front
A41: Quarter Sleeves Kurti | B41: Robin Blue, Round neck, light thread works in front | C41: Cotton | D41: Robin Blue | F41: Round neck | G41: light thread works in front
A42: Quarter Sleeves Kurti | B42: Purple with white floral print, Round neck, light thread works in front | C42: Cotton | D42: Purple with white floral print | F42: Round neck | G42: light thread works in front
A43: Quarter Sleeves Kurti | B43: SkyBlue with white floral print, Round neck, light thread works in front | C43: Cotton | D43: SkyBlue with white floral print | F43: Round neck | G43: light thread works in front
A44: Quarter Sleeves Kurti | B44: Yellow with white floral print, round neck, light thread works in front | C44: Cotton | D44: Yellow with white floral print | F44: round neck | G44: light thread works in front
A45: Quarter Sleeves Kurti | B45: Yellow, kalamkari print, aplic with DUCK thread works in front | C45: Cotton | D45: Yellow | E45: kalamkari print | G45: aplic with DUCK thread works in front
A46: Quarter Sleeves Kurti | B46: Blue, kalamkari print,Round neck, aplic with DUCK thread works in front | C46: Cotton | D46: Blue | E46: kalamkari print | F46: Round neck | G46: aplic with DUCK thread works in front
A47: Quarter Sleeves Kurti | B47: Green,kalamkari print, Round neck, aplic with DUCK thread works in front | C47: Cotton | D47: Green | E47: kalamkari print | F47: Round neck | G47: aplic with DUCK thread works in front
A48: Quarter Sleeves Kurti | B48: Maroon, kalamkari print, Round neck, aplic with DUCK thread works in front | C48: Cotton | E48: kalamkari print | F48: Round neck | G48: Maroon; aplic with DUCK thread works in front
A49: Quarter Sleeves Kurti | B49: Red with Floral print, V neck | C49: Cotton | D49: Red with Floral print | F49: V neck
A50: Quarter Sleeves Kurti | B50: Yellow with Floral print, V neck | C50: Cotton | D50: Yellow with Floral print | F50: V neck
A51: Quarter Sleeves Kurti | B51: Robin Blue with Floral print, V neck | C51: Cotton | D51: Robin Blue with Floral print | F51: V neck
A52: Quarter Sleeves Kurti | B52: Black with Floral print, V neck | C52: Cotton | D52: Black with Floral print | F52: V neck
A53: Quarter Sleeves Kurti | B53: Chocolate Brown, angrakha | C53: Cotton | G53: Chocolate Brown; angrakha
A54: Quarter Sleeves Kurti | B54: Red-White-Black kurti, Round Neck, thread work | C54: Cotton | D54: Red-White-Black kurti | F54: Round Neck | G54: thread work
A55: Quarter Sleeves Kurti | B55: Black-White-Red kurti, Round Neck, thread work | C55: Cotton | D55: Black-White-Red kurti | F55: Round Neck | G55: thread work
A56: Quarter Sleeves Kurti | B56: Pink, V Neck, angrakha style, thread work | C56: Cotton | D56: Pink | F56: V Neck | G56: angrakha style; thread work
A57: Quarter Sleeves Kurti | B57: Pink, Round Neck, angrakha style thread work | C57: Cotton | D57: Pink | F57: Round Neck | G57: angrakha style thread work
A58: Quarter Sleeves Kurti | B58: Maroon, Round Neck, Ajrakh print & thread work in front | C58: Cotton | E58: Ajrakh print & thread work in front | F58: Round Neck | G58: Maroon
A59: Quarter Sleeves Kurti | B59: Navy Blue, V Neck, Ajrakh Border around the neck | C59: Cotton | D59: Navy Blue | F59: V Neck; Ajrakh Border around the neck
A60: Quarter Sleeves Kurti | B60: Maroon, V Neck, thread work in front | C60: Reyon | F60: V Neck | G60: Maroon; thread work in front
A61: Noodle Kurti | B61: Zed black, Molmol,sleeveless, print and light thread work in front | C61: Cotton | D61: Zed black | E61: print and light thread work in front | G61: Molmol; sleeveless
A62: Noodle Kurti | B62: Ochre Yellow, sleeveless, print and light thread work in front | C62: Cotton | D62: Ochre Yellow | E62: print and light thread work in front | G62: sleeveless
A63: Noodle Kurti | B63: Maroon sleeveless, All over print and light thread work | C63: Cotton | E63: All over print and light thread work | G63: Maroon sleeveless
A64: Noodle Kurti | B64: Black sleeveless, All over print and light thread work | C64: Cotton | D64: Black sleeveless | E64: All over print and light thread work
A65: Noodle Kurti | B65: Chocolate Brown, sleeveless, All over print and light thread work | C65: Cotton | E65: All over print and light thread work | G65: Chocolate Brown; sleeveless
A66: Halter Neck Kurti | B66: Yellow, Sleeveless, Hacoba | C66: Cotton | D66: Yellow | G66: Sleeveless; Hacoba
A67: Sleeveless Kurti | B67: Black, Kalamkari all over printed | C67: Cotton | D67: Black | E67: Kalamkari all over printed
A68: Sleeveless Kurti | B68: Maroon, all over printed | C68: Cotton | E68: all over printed | G68: Maroon
A69: Sleeveless Kurti | B69: Yellow, all over White zig zag print, light thread works in front | C69: Cotton | D69: Yellow; all over White zig zag print | G69: light thread works in front
A70: Sleeveless Kurti | B70: Pink, all over White Floral print | C70: Cotton | D70: Pink; all over White Floral print
A71: Sleeveless Kurti | B71: Dark Green, all over White Floral print, light thread work in front | C71: Cotton | D71: Dark Green; all over White Floral print | G71: light thread work in front
A72: Sleeveless Kurti | B72: Gray, all over White Floral print, light thread work in front | C72: Cotton | D72: all over White Floral print | G72: Gray; light thread work in front
A73: Sleeveless Kurti | B73: white, Aplic work kurti | C73: Cotton | D73: white | G73: Aplic work kurti
A74: Sleeveless Kurti | B74: Black, Aplic work kurti | C74: Cotton | D74: Black | G74: Aplic work kurti
A75: Sleeveless Kurti | B75: Black and red kurti | C75: Cotton | D75: Black and red kurti
A76: Sleeveless Kurti | B76: Black, Angrakha style, V Neck, Lace work on neckline | C76: Cotton | D76: Black | F76: V Neck; Lace work on neckline | G76: Angrakha style
A77: Sleeveless Kurti | B77: Multi Colour, Angrakha style, V Neck, thread work in front KATHA WORK | C77: Cotton | F77: V Neck | G77: Multi Colour; Angrakha style; thread work in front KATHA WORK
A78: Sleeveless Kurti | B78: White with Multi Colour Strips, V Neck | C78: Cotton | D78: White with Multi Colour Strips | F78: V Neck
A79: Sleeveless Kurti | B79: Blue, All over sky blue & red thread work, round neck | C79: Cotton | D79: Blue; All over sky blue & red thread work | F79: round neck
A80: Sleeveless Kurti | B80: Magenta middle & white both side, round neck, light thread work | C80: Cotton | D80: Magenta middle & white both side | F80: round neck | G80: light thread work
A81: Sleeveless Kurti | B81: White with sky blue strips, round neck, light red strip thread work | C81: Cotton | D81: White with sky blue strips; light red strip thread work | F81: round neck
A82: Sleeveless Kurti | B82: Blue Bandni Kurti | C82: Cotton | D82: Blue Bandni Kurti
A83: Sleeveless Kurti | B83: Indigo, round neck, All over printed light red thread work | C83: Cotton | D83: All over printed light red thread work | F83: round neck | G83: Indigo
A84: Quarter Sleeves Kurti | B84: Maroon-Blue, angrakha style, lace thread work in front | C84: Modal Silk | D84: Maroon-Blue | G84: angrakha style; lace thread work in front
A85: Dress | B85: Bottle Green, Shirt collar, Sleeveless, floral Print | C85: Cotton + Rayon | D85: Bottle Green | E85: floral Print | G85: Shirt collar; Sleeveless
A86: Dress | B86: White with multi colour, Shirt collar, Sleeveless, floral Print | C86: Cotton + Rayon | D86: White with multi colour | E86: floral Print | G86: Shirt collar; Sleeveless
A87: Dress | B87: White, Hacoba gown all over thread work | C87: Cotton | D87: White | G87: Hacoba gown all over thread work
A88: Quarter Sleeves Kurti | B88: Purple Kurti | C88: Cotton | G88: Purple Kurti
A89: Noodle Kurti | B89: black-red Noodle Kurti | C89: Cotton | D89: black-red Noodle Kurti
A90: Sleeveless Kurti | B90: Light Green Kurti | C90: Cotton | D90: Light Green Kurti
A91: Sleevless Co-Ord Set | B91: chocolate colour solid colour co-ord set | C91: Imported | G91: chocolate colour solid colour co-ord set
A92: Sleevless Co-Ord Set | B92: Robin Blue colour solid colour co-ord set | C92: Imported | D92: Robin Blue colour solid colour co-ord set
A93: Dress | B93: Dark Green, solid colour, shirt coller dress | C93: Imported | D93: Dark Green | G93: solid colour; shirt coller dress
A94: Dress | B94: Cream colour, solid colour, shirt coller dress | C94: Imported | G94: Cream colour; solid colour; shirt coller dress
A95: Dress | B95: Pink full length dress, floral print, shirt coller dress | C95: Imported | D95: Pink full length dress | E95: floral print | G95: shirt coller dress
A96: Dress | B96: Gray full length dress, floral print, shirt coller dress | C96: Imported | E96: floral print | G96: Gray full length dress; shirt coller dress
A97: Dress | B97: White full length dress, floral print, shirt coller dress | C97: Imported | D97: White full length dress | E97: floral print | G97: shirt coller dress
A98: Dress | B98: Steel Blue full length dress, floral print, shirt coller dress | C98: Imported | D98: Steel Blue full length dress | E98: floral print | G98: shirt coller dress
A99: 3 Piece | B99: V neck , Quarter sleeves, robin blue, red and golden Havey thread and bites work | C99: Dola | D99: robin blue; red and golden Havey thread and bites work | F99: V neck | G99: Quarter sleeves
A100: 3 Piece | B100: V neck , Quarter sleeves, Pesta Green colour, red and golden Havey thread and bites work | C100: Dola | D100: Pesta Green colour; red and golden Havey thread and bites work | F100: V neck | G100: Quarter sleeves
...

Sheet check
D1: Expense Type | E1: Garments
A3: Row Labels | B3: Sum of Buy Price | D3: Row Labels | E3: Sum of Cost
A4: N G Garments | B4: 25300 | D4: N G Garments | E4: 26355 | F4: =GETPIVOTDATA("Cost",$D$3,"Shop Name","N G Garments")-GETPIVOTDATA("Buy Price",$A$3,"Shop Name","N G Garments") -> 1055
A5: Rudra Fashion | B5: 19620 | D5: Rudra Fashion | E5: 19845 | F5: =GETPIVOTDATA("Cost",$D$3,"Shop Name","Rudra Fashion")-GETPIVOTDATA("Buy Price",$A$3,"Shop Name","Rudra Fashion") -> 225
A6: RV Fashion | B6: 4670 | D6: RV Fashions | E6: 4670 | F6: =GETPIVOTDATA("Cost",$D$3,"Shop Name","RV Fashions")-GETPIVOTDATA("Buy Price",$A$3,"Shop Name","RV Fashion") -> 0
A7: Soma Collection | B7: 17560 | D7: Soma Collection | E7: 16065 | F7: =GETPIVOTDATA("Cost",$D$3,"Shop Name","Soma Collection")-GETPIVOTDATA("Buy Price",$A$3,"Shop Name","Soma Collection") -> -1495
A8: (blank) | D8: Grand Total | E8: 66935
A9: Grand Total | B9: 67150
